gemini_coder/__init__.py
gemini_coder/cli.py
gemini_coder/core/__init__.py
gemini_coder/core/config.py
gemini_coder/core/generator.py
gemini_coder/core/main.py
gemini_coder/core/processor.py
gemini_coder-0.1.2.dist-info/licenses/LICENSE
tests/__init__.py
tests/test_config.py
gemini_coder-0.1.2.dist-info/METADATA
gemini_coder-0.1.2.dist-info/WHEEL
gemini_coder-0.1.2.dist-info/entry_points.txt
gemini_coder-0.1.2.dist-info/top_level.txt
gemini_coder-0.1.2.dist-info/RECORD
