Metadata-Version: 2.4
Name: gemini-coder
Version: 0.1.2
Summary: A Python tool that uses Google's Gemini API to generate animated GIFs from text prompts
Home-page: https://github.com/daymade/gemini-coder
Author: Gemini Coder Contributors
Author-email: Gemini Coder Contributors <your.email@example.com>
Maintainer-email: Gemini Coder Contributors <your.email@example.com>
License-Expression: MIT
Project-URL: Homepage, https://github.com/daymade/gemini-coder
Project-URL: Bug Tracker, https://github.com/daymade/gemini-coder/issues
Project-URL: Documentation, https://github.com/daymade/gemini-coder#readme
Project-URL: Source Code, https://github.com/daymade/gemini-coder
Keywords: gemini,gif,animation,ai,google,generative,animation,pixel art
Classifier: Development Status :: 4 - Beta
Classifier: Intended Audience :: Developers
Classifier: Intended Audience :: End Users/Desktop
Classifier: Programming Language :: Python :: 3
Classifier: Programming Language :: Python :: 3.10
Classifier: Programming Language :: Python :: 3.11
Classifier: Programming Language :: Python :: 3.12
Classifier: Topic :: Multimedia :: Graphics
Classifier: Topic :: Utilities
Classifier: Topic :: Artistic Software
Classifier: Operating System :: OS Independent
Requires-Python: >=3.10
License-File: LICENSE
Requires-Dist: Pillow>=11.0.0
Requires-Dist: google-genai>=1.5.0
Requires-Dist: loguru>=0.7.0
Requires-Dist: python-dotenv>=1.0.0
Requires-Dist: tqdm>=4.65.0
Requires-Dist: imageio>=2.37.0
Dynamic: author
Dynamic: home-page
Dynamic: license-file
Dynamic: requires-python
